smartgridsolver/__init__.py
smartgridsolver-0.0.1.dist-info/METADATA
smartgridsolver-0.0.1.dist-info/WHEEL
smartgridsolver-0.0.1.dist-info/top_level.txt
smartgridsolver-0.0.1.dist-info/RECORD
