Metadata-Version: 2.4
Name: smartgridsolver
Version: 0.0.1
Summary: A Machine Learning Benchmark Suite for AC Optimal Power Flow.
Home-page: https://www.mit.edu/~arsam/
Author: Arsam Aryandoust
Author-email: Arsam Aryandoust <arsam@mit.edu>
License: MIT License
Project-URL: Source, https://github.com/ArsamAryandoust/SmartGridSolver
Project-URL: Documentation, https://readthedocs.org/projects/SmartGridSolver/
Keywords: Artificial Intelligence,ACOPF,Machine Learning
Classifier: Programming Language :: Python :: 3
Classifier: Operating System :: OS Independent
Requires-Python: >=3.9
Requires-Dist: numpy>=2.0
Requires-Dist: pandas>=2.0
Requires-Dist: matplotlib>=3.0.0
Requires-Dist: pyyaml>=6.0.0
